LICENSE
MANIFEST.in
README.md
setup.py
PyGEtoolbox/Download.py
PyGEtoolbox/Functions.py
PyGEtoolbox/PyGEtoolbox.py
PyGEtoolbox/__init__.py
PyGEtoolbox.egg-info/PKG-INFO
PyGEtoolbox.egg-info/SOURCES.txt
PyGEtoolbox.egg-info/dependency_links.txt
PyGEtoolbox.egg-info/requires.txt
PyGEtoolbox.egg-info/top_level.txt