Metadata-Version: 2.1
Name: PyGEtoolbox
Version: 0.0.3
Summary: Gene expression toolbox in Python
Home-page: https://github.com/firefly-cpp/PyGEtoolbox
Author: firefly-cpp
License: MIT
Platform: UNKNOWN
Classifier: Topic :: Scientific/Engineering
Classifier: Topic :: Software Development
